LICENSE
ml_lib/__init__.py
ml_lib/_metadata.py
ml_lib/bar_module.py
ml_lib/foo_module.py
ml_lib/data/test.yaml
ml_lib/data/nested_data/more_data.txt
ml_lib/data/nested_data/more_nested/even_more_data.txt
ml_lib/data/nested_data/more_nested/labels/red_label.txt
ml_lib/nested/__init__.py
ml_lib/nested/baz_module.py
aferro_ml_lib-0.7.2.dist-info/LICENSE
aferro_ml_lib-0.7.2.dist-info/METADATA
aferro_ml_lib-0.7.2.dist-info/WHEEL
aferro_ml_lib-0.7.2.dist-info/top_level.txt
aferro_ml_lib-0.7.2.dist-info/RECORD
