Metadata-Version: 2.1
Name: aferro-ml-lib
Version: 0.7.2
Summary: A nice library.
Home-page: https://github.com/andres-fr/python_ml_template
Author: aferro
Author-email: andres.fernandez@surrey.ac.uk
License: MIT
Platform: UNKNOWN
Classifier: Programming Language :: Python :: 3.6
Classifier: Operating System :: OS Independent
Requires-Python: >=3.6
